northern_lights_forecast/__init__.py
northern_lights_forecast/__main__.py
northern_lights_forecast/image_analysis.py
northern_lights_forecast/img.py
northern_lights_forecast/nlf_telegram_bot.py
northern_lights_forecast/northern_lights.py
northern_lights_forecast/savgol/savitzky_golay.py
northern_lights_forecast-4.1.4.dist-info/entry_points.txt
northern_lights_forecast-4.1.4.dist-info/LICENSE.rst
northern_lights_forecast-4.1.4.dist-info/WHEEL
northern_lights_forecast-4.1.4.dist-info/METADATA
northern_lights_forecast-4.1.4.dist-info/RECORD
