Metadata-Version: 2.1
Name: northern-lights-forecast
Version: 4.1.4
Summary: A simple web scraping northern lights forecast that automatically send a telegram notification during substorm events
Home-page: https://github.com/engeir/northern-lights-forecast
License: MIT
Author: Eirik Rolland Enger
Author-email: eirroleng@gmail.com
Requires-Python: >=3.8,<3.11
Classifier: License :: OSI Approved :: MIT License
Classifier: Programming Language :: Python :: 3
Classifier: Programming Language :: Python :: 3.10
Classifier: Programming Language :: Python :: 3.8
Classifier: Programming Language :: Python :: 3.9
Requires-Dist: click (>=7,<9)
Requires-Dist: importlib-metadata (>=4.12.0,<5.0.0)
Requires-Dist: matplotlib (>=3.5.1,<4.0.0)
Requires-Dist: numpy (>=1.22.1,<2.0.0)
Requires-Dist: pid (>=3.0.4,<4.0.0)
Requires-Dist: pyTelegramBotAPI (>=4.3.0,<5.0.0)
Requires-Dist: pytesseract (>=0.3.7,<0.4.0)
Requires-Dist: requests (>=2.27.1,<3.0.0)
Requires-Dist: telegram-send (>=0.25,<0.35)
Project-URL: Changelog, https://github.com/engeir/northern-lights-forecast/releases
Project-URL: Documentation, https://northern-lights-forecast.readthedocs.io
Project-URL: Repository, https://github.com/engeir/northern-lights-forecast
